br_navigator-0.0.4.dist-info/METADATA
br_navigator-0.0.4.dist-info/WHEEL
br_navigator/__init__.py
br_navigator/br_navigator.abi3.so
br_navigator-0.0.4.dist-info/RECORD
