Metadata-Version: 2.1
Name: br_navigator
Version: 0.0.4
Classifier: Framework :: Robot Framework
Classifier: Topic :: Scientific/Engineering
Classifier: Topic :: Software Development :: Embedded Systems
Classifier: Programming Language :: Rust
Summary: This package serves as the entry point for embedded applications using Python on Blue Robotics's Navigator
Requires-Python: >=3.7
Project-URL: Documentation, https://raultrombin.github.io/navigator-lib/
Project-URL: Repository, https://github.com/bluerobotics/navigator-lib
Project-URL: Homepage, https://bluerobotics.com/store/comm-control-power/control/navigator/
